pyqpanda3/__init__.py
pyqpanda3/core/__init__.py
pyqpanda3/core/core.cpython-313-darwin.so
pyqpanda3/core/core.pyi
pyqpanda3/core/msvcr120.dll
pyqpanda3/hamiltonian/__init__.py
pyqpanda3/hamiltonian/hamiltonian.cpython-313-darwin.so
pyqpanda3/hamiltonian/hamiltonian.pyi
pyqpanda3/intermediate_compiler/__init__.py
pyqpanda3/intermediate_compiler/intermediate_compiler.cpython-313-darwin.so
pyqpanda3/intermediate_compiler/intermediate_compiler.pyi
pyqpanda3/pilot_os/QPilotService.py
pyqpanda3/pilot_service/QPilotOSService.py
pyqpanda3/pilot_service/__init__.py
pyqpanda3/pilot_service/pilot_service.cpython-313-darwin.so
pyqpanda3/pilot_service/pilot_service.pyi
pyqpanda3/profiling/GprofExporter.py
pyqpanda3/profiling/QCircuitFeatures.py
pyqpanda3/profiling/Wrapper.py
pyqpanda3/profiling/__init__.py
pyqpanda3/profiling/data.py
pyqpanda3/profiling/exceptions.py
pyqpanda3/profiling/gprof2dot.py
pyqpanda3/profiling/profiling.py
pyqpanda3/profiling/routine_tree.py
pyqpanda3/profiling/strings.py
pyqpanda3/qcloud/__init__.py
pyqpanda3/qcloud/qcloud.cpython-313-darwin.so
pyqpanda3/qcloud/qcloud.pyi
pyqpanda3/quantum_info/__init__.py
pyqpanda3/quantum_info/quantum_info.cpython-313-darwin.so
pyqpanda3/quantum_info/quantum_info.pyi
pyqpanda3/transpilation/__init__.py
pyqpanda3/transpilation/transpilation.cpython-313-darwin.so
pyqpanda3/transpilation/transpilation.pyi
pyqpanda3/utils/__init__.py
pyqpanda3/utils/utils.cpython-313-darwin.so
pyqpanda3/vqcircuit/__init__.py
pyqpanda3/vqcircuit/vqcircuit.cpython-313-darwin.so
pyqpanda3/vqcircuit/vqcircuit.pyi
pyqpanda3-0.3.2.dist-info/METADATA
pyqpanda3-0.3.2.dist-info/WHEEL
pyqpanda3-0.3.2.dist-info/top_level.txt
pyqpanda3-0.3.2.dist-info/RECORD
