Metadata-Version: 2.4
Name: pyqpanda3
Version: 0.3.2
Summary: pyqpanda3 is Python wrapper of QPanda3.
Author: OriginQ
License: Apache Licence
Classifier: Development Status :: 4 - Beta
Classifier: Operating System :: MacOS :: MacOS X
Classifier: Operating System :: Microsoft :: Windows :: Windows 10
Classifier: Operating System :: POSIX :: Linux
Classifier: Topic :: Software Development :: Libraries :: Python Modules
Classifier: Programming Language :: Python
Classifier: Programming Language :: Python :: 3.9
Classifier: Programming Language :: Python :: 3.10
Classifier: Programming Language :: Python :: 3.11
Classifier: Programming Language :: Python :: 3.12
Classifier: Programming Language :: Python :: 3.13
Requires-Dist: numpy
Requires-Dist: matplotlib
Requires-Dist: Cython
Requires-Dist: networkx
Requires-Dist: mypy>=1.14.0
Requires-Dist: setuptools
Requires-Dist: graphviz
Dynamic: author
Dynamic: classifier
Dynamic: description
Dynamic: description-content-type
Dynamic: license
Dynamic: requires-dist
Dynamic: summary
